rallycli/__init__.py
rallycli/apis/__init__.py
rallycli/apis/artifact_api.py
rallycli/apis/attdefinition_api.py
rallycli/apis/project_api.py
rallycli/apis/quality_api.py
rallycli/apis/scm_api.py
rallycli/apis/timebox_api.py
rallycli/apis/user_api.py
rallycli/base_api.py
rallycli/errors/__init__.py
rallycli/errors/decorators.py
rallycli/errors/rally_errors.py
rallycli/models/__init__.py
rallycli/models/artifact_models.py
rallycli/models/base_models.py
rallycli/models/memento.py
rallycli/models/models.py
rallycli/models/type_names.py
rallycli/rally_api.py
rallycli/session_builder.py
rallycli/utils/__init__.py
rallycli/utils/logging.py
rallycli/utils/orig_utils.py
rallycli/utils/timer.py
rally_cli-2.0.3.dist-info/WHEEL
rally_cli-2.0.3.dist-info/METADATA
rally_cli-2.0.3.dist-info/RECORD
