Metadata-Version: 2.4
Name: rally-cli
Version: 2.0.3
Summary: Rally software API Client
Author: J. Andres Guerrero
Author-email: J. Andres Guerrero <juguerre@gmail.com>
License-Expression: MIT
Requires-Dist: requests>=2.28.1,<3
Requires-Dist: requests-futures>=1.0.0,<2
Requires-Dist: treelib>=1.6.1,<2
Requires-Dist: click>=8.1.3,<9
Requires-Dist: tqdm>=4.64.1,<5
Requires-Dist: simplejson>=3.18.0,<4
Requires-Dist: dateparser>=1.1.4,<2
Requires-Dist: pytz
Requires-Dist: pydantic>=2
Requires-Dist: coloredlogs>=15.0.1,<16
Requires-Dist: aiohttp>=3.8.3,<4
Requires-Dist: aiologger>=0.7.0,<1
Requires-Dist: python-dotenv>=1.1.0
Requires-Dist: toolz>=1.0.0
Requires-Python: >=3.9.0, <3.13
